statot/__init__.py
statot/cr.py
statot/inference.py
statot/keops.py
statot-0.0.14.dist-info/LICENSE
statot-0.0.14.dist-info/METADATA
statot-0.0.14.dist-info/WHEEL
statot-0.0.14.dist-info/top_level.txt
statot-0.0.14.dist-info/RECORD
