Metadata-Version: 2.1
Name: statot
Version: 0.0.14
Summary: statOT
Home-page: https://github.com/zsteve/statOT
Author: Stephen Zhang
Author-email: syz@math.ubc.ca
License: UNKNOWN
Platform: UNKNOWN
Classifier: Programming Language :: Python :: 3
Classifier: License :: OSI Approved :: MIT License
Classifier: Operating System :: OS Independent
Requires-Python: >=3.6
